{
	"disciplinas":	[{
			"nome":	"Aprendizado de Máquina",
			"codigo":	"MC886A",
			"ementa":	"Técnicas de aprendizado de máquina estatístico para classificação, agrupamento e detecção de outliers.",
			"sala":	"CB1/CB2",
			"horario":	"19:00-21:00/21:00-23:00",
			"comentario":	"Comentario feito para teste do UDP"
		}, {
			"nome":	"Introdução ao Processamento de Imagem Digital",
			"codigo":	"MC920A",
			"ementa":	"Fundamentos de imagem digital. Transformações geométricas. Transformações Radiométricas. Filtragem no domínio espacial. Filtragem no domínio da frequência. Técnicas de restauração. Introdução a segmentação. Introdução a morfologia matemática.",
			"sala":	"PB18",
			"horario":	"21:00-23:00/19:00-21:00",
			"comentario":	"Comentário inicial"
		}, {
			"nome":	"Projeto em Compiladores",
			"codigo":	"MC911A",
			"ementa":	"Implementação de um projeto prático na área de Compiladores.",
			"sala":	"CC02",
			"horario":	"14:00-18:00",
			"comentario":	"Comentário inicial"
		}, {
			"nome":	"Programação de Redes de Computadores",
			"codigo":	"MC833A",
			"ementa":	"Programação utilizando diferentes tecnologias de comunicação: sockets, TCP e UDP, e chamada de método remoto.",
			"sala":	"CC02",
			"horario":	"10:00-12:00",
			"comentario":	"Comentário inicial"
		}, {
			"nome":	"Economia para Engenharia",
			"codigo":	"CE738C",
			"ementa":	"O processo de produção visto pelas óticas micro e macroeconômicas. Produção e propriedade. Produção como técnica e como processo social. Agregação da produção. Mercados. Papel do governo.",
			"sala":	"IE01",
			"horario":	"19:00-21:00/21:00-23:00",
			"comentario":	"Comentário inicial"
		}]
}